docker_snapshot/__init__.py
docker_snapshot/container.py
docker_snapshot/images/__init__.py
docker_snapshot/images/rsync
docker_snapshot/settings.py
docker_snapshot/snapshot.py
docker_snapshot/utils.py
docker_snapshot-1.0.11.dist-info/METADATA
docker_snapshot-1.0.11.dist-info/WHEEL
docker_snapshot-1.0.11.dist-info/entry_points.txt
docker_snapshot-1.0.11.dist-info/RECORD
