Metadata-Version: 2.1
Name: docker-snapshot
Version: 1.0.11
Summary: `ds` is a development utility for managing snapshots inside a docker container.
Home-page: https://github.com/occamz/ds
Author: occamz
Requires-Python: >=3.9,<4.0
Classifier: Programming Language :: Python :: 3
Classifier: Programming Language :: Python :: 3.9
Classifier: Programming Language :: Python :: 3.10
Classifier: Programming Language :: Python :: 3.11
Classifier: Programming Language :: Python :: 3.12
Requires-Dist: PyYAML (>=6.0.1,<7.0.0)
Requires-Dist: click (>=8.1.7,<9.0.0)
Requires-Dist: click-aliases (>=1.0.4,<2.0.0)
Requires-Dist: colorama (>=0.4.6,<0.5.0)
Requires-Dist: docker (>=7.1.0,<8.0.0)
Requires-Dist: hruid (>=0.0.3,<0.0.4)
Requires-Dist: rich (>=13.7.1,<14.0.0)
Requires-Dist: six (>=1.16.0,<2.0.0)
Project-URL: Documentation, https://github.com/occamz/ds
